tcp_probe/__init__.py
tcp_probe/cli.py
tcp_probe/parser.py
tcp_probe/trace.py
tcp_probe/plot/__init__.py
tcp_probe/plot/plot.py
tcp_probe-0.0.4.dist-info/licenses/LICENSE
tcp_probe-0.0.4.dist-info/METADATA
tcp_probe-0.0.4.dist-info/WHEEL
tcp_probe-0.0.4.dist-info/entry_points.txt
tcp_probe-0.0.4.dist-info/top_level.txt
tcp_probe-0.0.4.dist-info/RECORD
